abx_plugin_mercury/__init__.py
abx_plugin_mercury/binaries.py
abx_plugin_mercury/config.py
abx_plugin_mercury/extractors.py
abx_plugin_mercury/mercury.py
abx_plugin_mercury-2024.10.28.dist-info/METADATA
abx_plugin_mercury-2024.10.28.dist-info/WHEEL
abx_plugin_mercury-2024.10.28.dist-info/entry_points.txt
abx_plugin_mercury-2024.10.28.dist-info/RECORD
